rabbitmq_wrapper
